aporiagen/counter.py
aporiagen/generator.py
aporiagen/main.py
aporiagen-0.0.2.dist-info/METADATA
aporiagen-0.0.2.dist-info/WHEEL
aporiagen-0.0.2.dist-info/entry_points.txt
aporiagen-0.0.2.dist-info/top_level.txt
aporiagen-0.0.2.dist-info/RECORD
