Metadata-Version: 2.4
Name: aporiagen
Version: 0.0.2
Summary: A program which generates random programs in the Aporia language
Author-email: Ephraim Siegfried <ephraim.siegfried@hotmail.com>
Requires-Python: >=3.10
Requires-Dist: aporia-interpreter>=0.1.12
